BloonsMacro/__init__.py
BloonsMacro/macros.py
BloonsMacro-0.0.1.dist-info/LICENSE
BloonsMacro-0.0.1.dist-info/METADATA
BloonsMacro-0.0.1.dist-info/WHEEL
BloonsMacro-0.0.1.dist-info/top_level.txt
BloonsMacro-0.0.1.dist-info/RECORD
